README.md
setup.py
gosnmp_traps_python/__init__.py
gosnmp_traps_python/common.py
gosnmp_traps_python/rpc_session.py
gosnmp_traps_python.egg-info/PKG-INFO
gosnmp_traps_python.egg-info/SOURCES.txt
gosnmp_traps_python.egg-info/dependency_links.txt
gosnmp_traps_python.egg-info/not-zip-safe
gosnmp_traps_python.egg-info/requires.txt
gosnmp_traps_python.egg-info/top_level.txt
gosnmp_traps_python/built/__init__.py
gosnmp_traps_python/built/build.py
gosnmp_traps_python/built/go.py
gosnmp_traps_python/built/gosnmp_traps_python_go.py